googletranslate/__init__.py
googletranslate/__main__.py
googletranslate/googletranslate.py
googletranslate/googletranslatetk.py
google_translate_for_goldendict-1.3.9.dist-info/LICENSE
google_translate_for_goldendict-1.3.9.dist-info/METADATA
google_translate_for_goldendict-1.3.9.dist-info/WHEEL
google_translate_for_goldendict-1.3.9.dist-info/top_level.txt
google_translate_for_goldendict-1.3.9.dist-info/RECORD
