Metadata-Version: 2.1
Name: google-translate-for-goldendict
Version: 1.3.9
Summary: Add Google translate to GoldenDict
Home-page: https://github.com/xinebf/google-translate-for-goldendict
Author: xinebf
Author-email: me@xinebf.com
License: UNKNOWN
Platform: UNKNOWN
Classifier: Programming Language :: Python :: 3
Classifier: License :: OSI Approved :: GNU General Public License v3 (GPLv3)
Classifier: Operating System :: OS Independent
Requires-Python: >=3.7
License-File: LICENSE
Requires-Dist: requests
